nonebot_plugin_randpic/__init__.py
nonebot_plugin_randpic/ali_oss.py
nonebot_plugin_randpic/compress.py
nonebot_plugin_randpic/config.py
nonebot_plugin_randpic/web.py
nonebot_plugin_randpic-1.0.5.dist-info/METADATA
nonebot_plugin_randpic-1.0.5.dist-info/WHEEL
nonebot_plugin_randpic-1.0.5.dist-info/licenses/LICENSE
nonebot_plugin_randpic-1.0.5.dist-info/RECORD
