Metadata-Version: 2.4
Name: nonebot-plugin-randpic
Version: 1.0.5
Summary: 一个通过指令随机发送你存储的图片的nonebot2插件
License: MIT
License-File: LICENSE
Author: HuParry
Author-email: hu_parry@qq.com
Requires-Python: >=3.8,<4.0
Classifier: License :: OSI Approved :: MIT License
Classifier: Programming Language :: Python :: 3
Classifier: Programming Language :: Python :: 3.8
Classifier: Programming Language :: Python :: 3.9
Classifier: Programming Language :: Python :: 3.10
Classifier: Programming Language :: Python :: 3.11
Classifier: Programming Language :: Python :: 3.12
Classifier: Programming Language :: Python :: 3.13
Classifier: Programming Language :: Python :: 3.14
Requires-Dist: aiosqlite (>=0.13.0,<0.14.0)
Requires-Dist: alibabacloud_oss_v2 (>=1.1.0)
Requires-Dist: httpx (>=0.20.0,<1.0.0)
Requires-Dist: nonebot-adapter-onebot (>=2.1.5,<3.0.0)
Requires-Dist: nonebot-plugin-localstore (>=0.6.0,<0.7.0)
Requires-Dist: nonebot2[fastapi] (>=2.0.0,<3.0.0)
Project-URL: Homepage, https://github.com/HuParry/nonebot-plugin-randpic
Project-URL: Repository, https://github.com/HuParry/nonebot-plugin-randpic
